{
  "project_info": {
    "project_number": "51170606668",
    "project_id": "promodofocusapp",
    "storage_bucket": "promodofocusapp.firebasestorage.app"
  },
  "client": [
    {
      "client_info": {
        "mobilesdk_app_id": "1:51170606668:android:0f350440ccc0b71f7f3ee9",
        "android_client_info": {
          "package_name": "com.example.promodoapp"
        }
      },
      "oauth_client": [],
      "api_key": [
        {
          "current_key": "AIzaSyD7D5I_PiC3tZ-Yzk12itFISqFT3EN4ZRM"
        }
      ],
      "services": {
        "appinvite_service": {
          "other_platform_oauth_client": []
        }
      }
    }
  ],
  "configuration_version": "1"
}